cybrid_api_organization/__init__.py
cybrid_api_organization/api_client.py
cybrid_api_organization/configuration.py
cybrid_api_organization/exceptions.py
cybrid_api_organization/model_utils.py
cybrid_api_organization/rest.py
cybrid_api_organization/api/__init__.py
cybrid_api_organization/api/organizations_organization_api.py
cybrid_api_organization/api/subscription_deliveries_organization_api.py
cybrid_api_organization/api/subscription_events_organization_api.py
cybrid_api_organization/api/subscriptions_organization_api.py
cybrid_api_organization/apis/__init__.py
cybrid_api_organization/model/__init__.py
cybrid_api_organization/model/error_response.py
cybrid_api_organization/model/list_request_page.py
cybrid_api_organization/model/list_request_per_page.py
cybrid_api_organization/model/organization.py
cybrid_api_organization/model/patch_organization.py
cybrid_api_organization/model/post_subscription.py
cybrid_api_organization/model/post_subscription_delivery.py
cybrid_api_organization/model/subscription.py
cybrid_api_organization/model/subscription_delivery.py
cybrid_api_organization/model/subscription_delivery_list.py
cybrid_api_organization/model/subscription_environment.py
cybrid_api_organization/model/subscription_event.py
cybrid_api_organization/model/subscription_event_list.py
cybrid_api_organization/model/subscription_list.py
cybrid_api_organization/model/subscription_state.py
cybrid_api_organization/model/subscription_type.py
cybrid_api_organization/models/__init__.py
cybrid_api_organization_python-0.126.83.dist-info/METADATA
cybrid_api_organization_python-0.126.83.dist-info/WHEEL
cybrid_api_organization_python-0.126.83.dist-info/top_level.txt
cybrid_api_organization_python-0.126.83.dist-info/RECORD
